setup.cfg
setup.py
FileDownloader/FileDownloader.py
FileDownloader/__init__.py
FileDownloader/util.py
FileDownloader.egg-info/PKG-INFO
FileDownloader.egg-info/SOURCES.txt
FileDownloader.egg-info/dependency_links.txt
FileDownloader.egg-info/top_level.txt