Metadata-Version: 1.1
Name: FileDownloader
Version: 0.0.2
Summary: download file in multi threads
Home-page: https://github.com/yangsibai/py-FileDownloader
Author: massimo
Author-email: yangsibai@gmail.com
License: MIT
Keywords: download multi threads
Platform: UNKNOWN
Classifier: Development Status :: 3 - Alpha
Classifier: Topic :: Internet :: WWW/HTTP
Classifier: License :: OSI Approved :: MIT License
